fxf/__init__.py
fxf/core.py
fxf/logger.py
fxf/types.py
fxf-0.1.0.dist-info/METADATA
fxf-0.1.0.dist-info/WHEEL
fxf-0.1.0.dist-info/top_level.txt
fxf-0.1.0.dist-info/RECORD
