Metadata-Version: 2.4
Name: fxf
Version: 0.1.0
Summary: FXF — Files X Folders. Simple and safe filesystem helper.
Author: maksalmaz
License: MIT
Requires-Python: >=3.8
